nup_poder_judiciario/__init__.py
nup_poder_judiciario/nup.py
nup_poder_judiciario-0.0.5.dist-info/LICENSE
nup_poder_judiciario-0.0.5.dist-info/METADATA
nup_poder_judiciario-0.0.5.dist-info/WHEEL
nup_poder_judiciario-0.0.5.dist-info/top_level.txt
nup_poder_judiciario-0.0.5.dist-info/RECORD
