Metadata-Version: 2.1
Name: nup_poder_judiciario
Version: 0.0.5
Summary: Funcionalidades relacionadas à numeração única de processos do Poder Judiciário
Author-email: Rafael Leite <rafxel@gmail.com>
Project-URL: Homepage, https://github.com/rafxel/nup_poder_judiciario
Project-URL: Bug Tracker, https://github.com/rafxel/nup_poder_judiciario/issues
Classifier: Programming Language :: Python :: 3
Classifier: License :: OSI Approved :: MIT License
Classifier: Operating System :: OS Independent
Requires-Python: >=3.7
License-File: LICENSE
